setup.py
OhlohWidgetsMacro.egg-info/PKG-INFO
OhlohWidgetsMacro.egg-info/SOURCES.txt
OhlohWidgetsMacro.egg-info/dependency_links.txt
OhlohWidgetsMacro.egg-info/entry_points.txt
OhlohWidgetsMacro.egg-info/not-zip-safe
OhlohWidgetsMacro.egg-info/requires.txt
OhlohWidgetsMacro.egg-info/top_level.txt
ohloh_widgets/__init__.py
ohloh_widgets/api.py
ohloh_widgets/macro.py
ohloh_widgets/modifiers.py
ohloh_widgets/util.py
ohloh_widgets/validation.py
ohloh_widgets/lib/__init__.py
ohloh_widgets/lib/attribute_dict.py
ohloh_widgets/lib/simple_super.py
ohloh_widgets/lib/testcase.py
tests/__init__.py
tests/macro_test.py
tests/var_args_parsing_schema_test.py