Metadata-Version: 1.0
Name: OhlohWidgetsMacro
Version: 0.2
Summary: Trac macro to embed Ohloh widgets
Home-page: http://www.schwarz.eu/opensource/projects/ohloh_widgets_macro
Author: Felix Schwarz
Author-email: felix.schwarz@oss.schwarz.eu
License: MIT
Download-URL: http://www.schwarz.eu/opensource/projects/ohloh_widgets_macro/download/0.2
Platform: UNKNOWN
Classifier: Development Status :: 4 - Beta
Classifier: Framework :: Trac
Classifier: Intended Audience :: System Administrators
Classifier: License :: OSI Approved :: MIT License
Classifier: Operating System :: OS Independent
Classifier: Programming Language :: Python
Classifier: Topic :: Software Development :: Libraries :: Python Modules
